SecureMorph/__init__.py
SecureMorph/main.py
SecureMorph/prompts.py
securemorph-2025.12.20172640.dist-info/METADATA
securemorph-2025.12.20172640.dist-info/WHEEL
securemorph-2025.12.20172640.dist-info/top_level.txt
securemorph-2025.12.20172640.dist-info/RECORD
