Metadata-Version: 2.4
Name: SecureMorph
Version: 2025.12.20172640
Summary: The new package is designed to process text inputs related to advanced security concepts, such as secrets erasure upon observation. It utilizes structured pattern matching to interpret user instructio
Author-email: SecureMorph <hi@eugene.plus>
License: MIT
Project-URL: Homepage, https://github.com/chigwell/SecureMorph
Requires-Python: >=3.9
Requires-Dist: langchain-llm7>=0.0.0
Requires-Dist: llmatch-messages>=0.0.0
Requires-Dist: langchain-core>=0.3.0
